commi/__init__.py
commi/cmd.py
commi/commit_message.py
commi/logs.py
commi/run.py
commi-3.0.3.dist-info/LICENSE
commi-3.0.3.dist-info/METADATA
commi-3.0.3.dist-info/WHEEL
commi-3.0.3.dist-info/entry_points.txt
commi-3.0.3.dist-info/RECORD
