Metadata-Version: 2.1
Name: commi
Version: 3.0.3
Summary: AI-powered Git commit message generator.
Author: Mahmoud Emad
Author-email: mahmmoud.hassanein@gmail.com
Requires-Python: >=3.12,<4.0
Classifier: Programming Language :: Python :: 3
Classifier: Programming Language :: Python :: 3.12
Classifier: Programming Language :: Python :: 3.13
Requires-Dist: black (>=25.1.0,<26.0.0)
Requires-Dist: colorlog (>=6.9.0,<7.0.0)
Requires-Dist: gitpython (>=3.1.43,<4.0.0)
Requires-Dist: google-generativeai (>=0.8.3,<0.9.0)
Requires-Dist: grpcio (>=1.62.0,<2.0.0)
Requires-Dist: mypy (>=1.15.0,<2.0.0)
Requires-Dist: packaging (>=24.2,<25.0)
Requires-Dist: pyfiglet (>=1.0.2,<2.0.0)
Requires-Dist: pyperclip (>=1.9.0,<2.0.0)
Requires-Dist: pytest (>=8.3.4,<9.0.0)
Requires-Dist: python-decouple (>=3.8,<4.0)
Requires-Dist: requests (>=2.32.3,<3.0.0)
Requires-Dist: ruff (>=0.9.6,<0.10.0)
Requires-Dist: shiv (>=1.0.8,<2.0.0)
Requires-Dist: toml (>=0.10.2,<0.11.0)
Requires-Dist: types-requests (>=2.32.0.20250328,<3.0.0.0)
Requires-Dist: types-toml (>=0.10.8.20240310,<0.11.0.0)
